{"commitInfo":{"timestamp":1775366470505,"operation":"STREAMING UPDATE","operationParameters":{"outputMode":"Append","queryId":"2ab881f7-46a8-46ac-a5c4-f56ccaad0681","epochId":"47"},"readVersion":7,"isolationLevel":"Serializable","isBlindAppend":true,"operationMetrics":{"numRemovedFiles":"0","numOutputRows":"71","numOutputBytes":"14848","numAddedFiles":"3"},"engineInfo":"Apache-Spark/3.5.8 Delta-Lake/3.3.2","txnId":"4825c45e-4eba-424e-8c56-a1f606de2bb4"}}
{"txn":{"appId":"2ab881f7-46a8-46ac-a5c4-f56ccaad0681","version":47,"lastUpdated":1775366470504}}
{"add":{"path":"part-00000-eea964b2-ff76-422e-a8a8-3acc04e61fcb-c000.snappy.parquet","partitionValues":{},"size":4863,"modificationTime":1775366470494,"dataChange":true,"stats":"{\"numRecords\":22,\"minValues\":{\"raw_json\":\"{\\\"id\\\": \\\"Ugw2jgB3tfNTPUpgMFl4AaAB\",\"topic\":\"btc_yt\",\"partition\":1,\"offset\":181,\"kafka_timestamp\":\"2026-04-05T10:51:08.687+05:30\"},\"maxValues\":{\"raw_json\":\"{\\\"id\\\": \\\"UgzHMfqZsm_1RlUStNJ4AaAB\",\"topic\":\"btc_yt\",\"partition\":1,\"offset\":202,\"kafka_timestamp\":\"2026-04-05T10:51:09.446+05:30\"},\"nullCount\":{\"raw_json\":0,\"topic\":0,\"partition\":0,\"offset\":0,\"kafka_timestamp\":0}}"}}
{"add":{"path":"part-00001-729ae62f-7e6e-4f57-9030-f47c1ba2c555-c000.snappy.parquet","partitionValues":{},"size":5106,"modificationTime":1775366470496,"dataChange":true,"stats":"{\"numRecords\":27,\"minValues\":{\"raw_json\":\"{\\\"id\\\": \\\"Ugw3mMW5UOditjgyu554AaAB\",\"topic\":\"btc_yt\",\"partition\":2,\"offset\":154,\"kafka_timestamp\":\"2026-04-05T10:51:08.682+05:30\"},\"maxValues\":{\"raw_json\":\"{\\\"id\\\": \\\"UgzQGKCODnBPTbjFoeF4AaAB\",\"topic\":\"btc_yt\",\"partition\":2,\"offset\":180,\"kafka_timestamp\":\"2026-04-05T10:51:09.449+05:30\"},\"nullCount\":{\"raw_json\":0,\"topic\":0,\"partition\":0,\"offset\":0,\"kafka_timestamp\":0}}"}}
{"add":{"path":"part-00002-e4b7b61a-8fd8-486c-af8d-a623aed78281-c000.snappy.parquet","partitionValues":{},"size":4879,"modificationTime":1775366470495,"dataChange":true,"stats":"{\"numRecords\":22,\"minValues\":{\"raw_json\":\"{\\\"id\\\": \\\"Ugw2imwkaExh2FPwnU54AaAB\",\"topic\":\"btc_yt\",\"partition\":0,\"offset\":159,\"kafka_timestamp\":\"2026-04-05T10:51:08.679+05:30\"},\"maxValues\":{\"raw_json\":\"{\\\"id\\\": \\\"Ugzr1F8h7Xm5LnYUJKJ4AaAB\",\"topic\":\"btc_yt\",\"partition\":0,\"offset\":180,\"kafka_timestamp\":\"2026-04-05T10:51:09.440+05:30\"},\"nullCount\":{\"raw_json\":0,\"topic\":0,\"partition\":0,\"offset\":0,\"kafka_timestamp\":0}}"}}
